{"zone": "SE-SE1", "history": [{"zone": "SE-SE1", "datetime": "2024-12-16T13:00:00.000Z", "updatedAt": "2024-12-16T16:29:22.488Z", "createdAt": "2024-12-13T13:42:04.931Z", "powerConsumptionBreakdown": {"nuclear": 0, "geothermal": 0, "biomass": 0, "coal": 0, "wind": 377, "solar": 0, "hydro": 1422, "gas": 0, "oil": 0, "unknown": 12, "hydro discharge": 0, "battery discharge": 0}, "powerProductionBreakdown": {"nuclear": null, "geothermal": null, "biomass": null, "coal": null, "wind": 128, "solar": 0, "hydro": 1842, "gas": null, "oil": null, "unknown": 18, "hydro discharge": null, "battery discharge": null}, "powerImportBreakdown": {"FI": 0, "NO-NO4": 0, "SE-SE2": 1054}, "powerExportBreakdown": {"FI": 1176, "NO-NO4": 55, "SE-SE2": 0}, "fossilFreePercentage": 100, "renewablePercentage": 100, "powerConsumptionTotal": 1811, "powerProductionTotal": 1988, "powerImportTotal": 1054, "powerExportTotal": 1231, "isEstimated": false, "estimationMethod": null}, {"zone": "SE-SE1", "datetime": "2024-12-16T14:00:00.000Z", "updatedAt": "2024-12-16T17:44:00.479Z", "createdAt": "2024-12-13T14:42:29.433Z", "powerConsumptionBreakdown": {"nuclear": 0, "geothermal": 0, "biomass": 0, "coal": 0, "wind": 453, "solar": 0, "hydro": 1392, "gas": 1, "oil": 0, "unknown": 13, "hydro discharge": 0, "battery discharge": 0}, "powerProductionBreakdown": {"nuclear": null, "geothermal": null, "biomass": null, "coal": null, "wind": 158, "solar": 0, "hydro": 1681, "gas": null, "oil": null, "unknown": 18, "hydro discharge": null, "battery discharge": null}, "powerImportBreakdown": {"FI": 0, "NO-NO4": 40, "SE-SE2": 1167}, "powerExportBreakdown": {"FI": 1206, "NO-NO4": 0, "SE-SE2": 0}, "fossilFreePercentage": 100, "renewablePercentage": 100, "powerConsumptionTotal": 1858, "powerProductionTotal": 1857, "powerImportTotal": 1207, "powerExportTotal": 1206, "isEstimated": false, "estimationMethod": null}, {"zone": "SE-SE1", "datetime": "2024-12-16T15:00:00.000Z", "updatedAt": "2024-12-16T18:42:45.744Z", "createdAt": "2024-12-13T15:44:21.260Z", "powerConsumptionBreakdown": {"nuclear": 0, "geothermal": 0, "biomass": 0, "coal": 0, "wind": 414, "solar": 0, "hydro": 1375, "gas": 1, "oil": 0, "unknown": 12, "hydro discharge": 0, "battery discharge": 0}, "powerProductionBreakdown": {"nuclear": null, "geothermal": null, "biomass": null, "coal": null, "wind": 174, "solar": 0, "hydro": 1751, "gas": null, "oil": null, "unknown": 18, "hydro discharge": null, "battery discharge": null}, "powerImportBreakdown": {"FI": 0, "NO-NO4": 55, "SE-SE2": 1008}, "powerExportBreakdown": {"FI": 1203, "NO-NO4": 0, "SE-SE2": 0}, "fossilFreePercentage": 100, "renewablePercentage": 100, "powerConsumptionTotal": 1803, "powerProductionTotal": 1943, "powerImportTotal": 1063, "powerExportTotal": 1203, "isEstimated": false, "estimationMethod": null}, {"zone": "SE-SE1", "datetime": "2024-12-16T16:00:00.000Z", "updatedAt": "2024-12-16T19:42:27.679Z", "createdAt": "2024-12-13T16:41:27.781Z", "powerConsumptionBreakdown": {"nuclear": 0, "geothermal": 0, "biomass": 0, "coal": 0, "wind": 453, "solar": 0, "hydro": 1437, "gas": 0, "oil": 0, "unknown": 13, "hydro discharge": 0, "battery discharge": 0}, "powerProductionBreakdown": {"nuclear": null, "geothermal": null, "biomass": null, "coal": null, "wind": 219, "solar": 0, "hydro": 1811, "gas": null, "oil": null, "unknown": 19, "hydro discharge": null, "battery discharge": null}, "powerImportBreakdown": {"FI": 0, "NO-NO4": 0, "SE-SE2": 1001}, "powerExportBreakdown": {"FI": 1098, "NO-NO4": 49, "SE-SE2": 0}, "fossilFreePercentage": 100, "renewablePercentage": 100, "powerConsumptionTotal": 1903, "powerProductionTotal": 2049, "powerImportTotal": 1001, "powerExportTotal": 1147, "isEstimated": false, "estimationMethod": null}, {"zone": "SE-SE1", "datetime": "2024-12-16T17:00:00.000Z", "updatedAt": "2024-12-16T21:43:33.714Z", "createdAt": "2024-12-13T17:44:34.463Z", "powerConsumptionBreakdown": {"nuclear": 0, "geothermal": 0, "biomass": 0, "coal": 0, "wind": 475, "solar": 0, "hydro": 1337, "gas": 0, "oil": 0, "unknown": 13, "hydro discharge": 0, "battery discharge": 0}, "powerProductionBreakdown": {"nuclear": null, "geothermal": null, "biomass": null, "coal": null, "wind": 269, "solar": 0, "hydro": 1646, "gas": null, "oil": null, "unknown": 19, "hydro discharge": null, "battery discharge": null}, "powerImportBreakdown": {"FI": 0, "NO-NO4": 12, "SE-SE2": 940}, "powerExportBreakdown": {"FI": 1060, "NO-NO4": 0, "SE-SE2": 0}, "fossilFreePercentage": 100, "renewablePercentage": 100, "powerConsumptionTotal": 1826, "powerProductionTotal": 1934, "powerImportTotal": 952, "powerExportTotal": 1060, "isEstimated": false, "estimationMethod": null}, {"zone": "SE-SE1", "datetime": "2024-12-16T18:00:00.000Z", "updatedAt": "2024-12-16T21:43:49.885Z", "createdAt": "2024-12-13T18:42:53.741Z", "powerConsumptionBreakdown": {"nuclear": 0, "geothermal": 0, "biomass": 0, "coal": 0, "wind": 528, "solar": 0, "hydro": 1331, "gas": 0, "oil": 0, "unknown": 14, "hydro discharge": 0, "battery discharge": 0}, "powerProductionBreakdown": {"nuclear": null, "geothermal": null, "biomass": null, "coal": null, "wind": 368, "solar": 0, "hydro": 1614, "gas": null, "oil": null, "unknown": 19, "hydro discharge": null, "battery discharge": null}, "powerImportBreakdown": {"FI": 0, "NO-NO4": 0, "SE-SE2": 844}, "powerExportBreakdown": {"FI": 874, "NO-NO4": 99, "SE-SE2": 0}, "fossilFreePercentage": 100, "renewablePercentage": 100, "powerConsumptionTotal": 1872, "powerProductionTotal": 2001, "powerImportTotal": 844, "powerExportTotal": 973, "isEstimated": false, "estimationMethod": null}, {"zone": "SE-SE1", "datetime": "2024-12-16T19:00:00.000Z", "updatedAt": "2024-12-16T22:45:34.801Z", "createdAt": "2024-12-13T19:44:00.560Z", "powerConsumptionBreakdown": {"nuclear": 0, "geothermal": 0, "biomass": 0, "coal": 0, "wind": 614, "solar": 0, "hydro": 1247, "gas": 0, "oil": 0, "unknown": 13, "hydro discharge": 0, "battery discharge": 0}, "powerProductionBreakdown": {"nuclear": null, "geothermal": null, "biomass": null, "coal": null, "wind": 448, "solar": 0, "hydro": 1485, "gas": null, "oil": null, "unknown": 19, "hydro discharge": null, "battery discharge": null}, "powerImportBreakdown": {"FI": 0, "NO-NO4": 0, "SE-SE2": 1050}, "powerExportBreakdown": {"FI": 1049, "NO-NO4": 79, "SE-SE2": 0}, "fossilFreePercentage": 100, "renewablePercentage": 100, "powerConsumptionTotal": 1874, "powerProductionTotal": 1952, "powerImportTotal": 1050, "powerExportTotal": 1128, "isEstimated": false, "estimationMethod": null}, {"zone": "SE-SE1", "datetime": "2024-12-16T20:00:00.000Z", "updatedAt": "2024-12-16T23:42:48.066Z", "createdAt": "2024-12-13T20:42:19.892Z", "powerConsumptionBreakdown": {"nuclear": 0, "geothermal": 0, "biomass": 0, "coal": 0, "wind": 631, "solar": 0, "hydro": 1237, "gas": 0, "oil": 0, "unknown": 13, "hydro discharge": 0, "battery discharge": 0}, "powerProductionBreakdown": {"nuclear": null, "geothermal": null, "biomass": null, "coal": null, "wind": 475, "solar": 0, "hydro": 1466, "gas": null, "oil": null, "unknown": 19, "hydro discharge": null, "battery discharge": null}, "powerImportBreakdown": {"FI": 0, "NO-NO4": 0, "SE-SE2": 1047}, "powerExportBreakdown": {"FI": 1060, "NO-NO4": 66, "SE-SE2": 0}, "fossilFreePercentage": 100, "renewablePercentage": 100, "powerConsumptionTotal": 1881, "powerProductionTotal": 1960, "powerImportTotal": 1047, "powerExportTotal": 1126, "isEstimated": false, "estimationMethod": null}, {"zone": "SE-SE1", "datetime": "2024-12-16T21:00:00.000Z", "updatedAt": "2024-12-17T00:44:01.268Z", "createdAt": "2024-12-13T21:42:39.310Z", "powerConsumptionBreakdown": {"nuclear": 0, "geothermal": 0, "biomass": 0, "coal": 0, "wind": 578, "solar": 0, "hydro": 1083, "gas": 0, "oil": 0, "unknown": 13, "hydro discharge": 0, "battery discharge": 0}, "powerProductionBreakdown": {"nuclear": null, "geothermal": null, "biomass": null, "coal": null, "wind": 401, "solar": 0, "hydro": 1263, "gas": null, "oil": null, "unknown": 19, "hydro discharge": null, "battery discharge": null}, "powerImportBreakdown": {"FI": 0, "NO-NO4": 0, "SE-SE2": 1111}, "powerExportBreakdown": {"FI": 1057, "NO-NO4": 63, "SE-SE2": 0}, "fossilFreePercentage": 100, "renewablePercentage": 100, "powerConsumptionTotal": 1674, "powerProductionTotal": 1683, "powerImportTotal": 1111, "powerExportTotal": 1120, "isEstimated": false, "estimationMethod": null}, {"zone": "SE-SE1", "datetime": "2024-12-16T22:00:00.000Z", "updatedAt": "2024-12-17T01:45:58.208Z", "createdAt": "2024-12-13T22:42:59.292Z", "powerConsumptionBreakdown": {"nuclear": 0, "geothermal": 0, "biomass": 0, "coal": 0, "wind": 618, "solar": 0, "hydro": 1049, "gas": 0, "oil": 0, "unknown": 17, "hydro discharge": 0, "battery discharge": 0}, "powerProductionBreakdown": {"nuclear": null, "geothermal": null, "biomass": null, "coal": null, "wind": 364, "solar": 0, "hydro": 988, "gas": null, "oil": null, "unknown": 20, "hydro discharge": null, "battery discharge": null}, "powerImportBreakdown": {"FI": 0, "NO-NO4": 0, "SE-SE2": 776}, "powerExportBreakdown": {"FI": 245, "NO-NO4": 219, "SE-SE2": 0}, "fossilFreePercentage": 100, "renewablePercentage": 100, "powerConsumptionTotal": 1684, "powerProductionTotal": 1372, "powerImportTotal": 776, "powerExportTotal": 464, "isEstimated": false, "estimationMethod": null}, {"zone": "SE-SE1", "datetime": "2024-12-16T23:00:00.000Z", "updatedAt": "2024-12-17T06:45:32.248Z", "createdAt": "2024-12-13T23:42:43.073Z", "powerConsumptionBreakdown": {"nuclear": 0, "geothermal": 0, "biomass": 0, "coal": 0, "wind": 820, "solar": 0, "hydro": 932, "gas": 0, "oil": 0, "unknown": 19, "hydro discharge": 0, "battery discharge": 0}, "powerProductionBreakdown": {"nuclear": null, "geothermal": null, "biomass": null, "coal": null, "wind": 448, "solar": 0, "hydro": 764, "gas": null, "oil": null, "unknown": 20, "hydro discharge": null, "battery discharge": null}, "powerImportBreakdown": {"FI": 0, "NO-NO4": 0, "SE-SE2": 795}, "powerExportBreakdown": {"FI": 18, "NO-NO4": 237, "SE-SE2": 0}, "fossilFreePercentage": 100, "renewablePercentage": 100, "powerConsumptionTotal": 1772, "powerProductionTotal": 1232, "powerImportTotal": 795, "powerExportTotal": 255, "isEstimated": false, "estimationMethod": null}, {"zone": "SE-SE1", "datetime": "2024-12-17T00:00:00.000Z", "updatedAt": "2024-12-17T06:45:03.541Z", "createdAt": "2024-12-14T00:41:38.097Z", "powerConsumptionBreakdown": {"nuclear": 2, "geothermal": 0, "biomass": 0, "coal": 0, "wind": 892, "solar": 0, "hydro": 742, "gas": 0, "oil": 0, "unknown": 19, "hydro discharge": 0, "battery discharge": 0}, "powerProductionBreakdown": {"nuclear": null, "geothermal": null, "biomass": null, "coal": null, "wind": 500, "solar": 0, "hydro": 536, "gas": null, "oil": null, "unknown": 20, "hydro discharge": null, "battery discharge": null}, "powerImportBreakdown": {"FI": 5, "NO-NO4": 0, "SE-SE2": 903}, "powerExportBreakdown": {"FI": 0, "NO-NO4": 309, "SE-SE2": 0}, "fossilFreePercentage": 100, "renewablePercentage": 100, "powerConsumptionTotal": 1655, "powerProductionTotal": 1056, "powerImportTotal": 908, "powerExportTotal": 309, "isEstimated": false, "estimationMethod": null}, {"zone": "SE-SE1", "datetime": "2024-12-17T01:00:00.000Z", "updatedAt": "2024-12-17T06:45:32.248Z", "createdAt": "2024-12-14T01:43:27.790Z", "powerConsumptionBreakdown": {"nuclear": 0, "geothermal": 0, "biomass": 0, "coal": 0, "wind": 926, "solar": 0, "hydro": 909, "gas": 0, "oil": 0, "unknown": 18, "hydro discharge": 0, "battery discharge": 0}, "powerProductionBreakdown": {"nuclear": null, "geothermal": null, "biomass": null, "coal": null, "wind": 438, "solar": 0, "hydro": 728, "gas": null, "oil": null, "unknown": 21, "hydro discharge": null, "battery discharge": null}, "powerImportBreakdown": {"FI": 0, "NO-NO4": 0, "SE-SE2": 1294}, "powerExportBreakdown": {"FI": 367, "NO-NO4": 261, "SE-SE2": 0}, "fossilFreePercentage": 100, "renewablePercentage": 100, "powerConsumptionTotal": 1853, "powerProductionTotal": 1187, "powerImportTotal": 1294, "powerExportTotal": 628, "isEstimated": false, "estimationMethod": null}, {"zone": "SE-SE1", "datetime": "2024-12-17T02:00:00.000Z", "updatedAt": "2024-12-17T06:45:32.248Z", "createdAt": "2024-12-14T02:44:00.219Z", "powerConsumptionBreakdown": {"nuclear": 0, "geothermal": 0, "biomass": 0, "coal": 0, "wind": 914, "solar": 0, "hydro": 912, "gas": 0, "oil": 0, "unknown": 17, "hydro discharge": 0, "battery discharge": 0}, "powerProductionBreakdown": {"nuclear": null, "geothermal": null, "biomass": null, "coal": null, "wind": 349, "solar": 0, "hydro": 756, "gas": null, "oil": null, "unknown": 21, "hydro discharge": null, "battery discharge": null}, "powerImportBreakdown": {"FI": 0, "NO-NO4": 0, "SE-SE2": 1593}, "powerExportBreakdown": {"FI": 678, "NO-NO4": 198, "SE-SE2": 0}, "fossilFreePercentage": 100, "renewablePercentage": 100, "powerConsumptionTotal": 1843, "powerProductionTotal": 1126, "powerImportTotal": 1593, "powerExportTotal": 876, "isEstimated": false, "estimationMethod": null}, {"zone": "SE-SE1", "datetime": "2024-12-17T03:00:00.000Z", "updatedAt": "2024-12-17T07:44:08.135Z", "createdAt": "2024-12-14T03:42:52.463Z", "powerConsumptionBreakdown": {"nuclear": 0, "geothermal": 0, "biomass": 0, "coal": 0, "wind": 786, "solar": 0, "hydro": 987, "gas": 3, "oil": 0, "unknown": 17, "hydro discharge": 0, "battery discharge": 0}, "powerProductionBreakdown": {"nuclear": null, "geothermal": null, "biomass": null, "coal": null, "wind": 228, "solar": 0, "hydro": 847, "gas": null, "oil": null, "unknown": 21, "hydro discharge": null, "battery discharge": null}, "powerImportBreakdown": {"FI": 0, "NO-NO4": 99, "SE-SE2": 1614}, "powerExportBreakdown": {"FI": 1017, "NO-NO4": 0, "SE-SE2": 0}, "fossilFreePercentage": 100, "renewablePercentage": 100, "powerConsumptionTotal": 1792, "powerProductionTotal": 1096, "powerImportTotal": 1713, "powerExportTotal": 1017, "isEstimated": false, "estimationMethod": null}, {"zone": "SE-SE1", "datetime": "2024-12-17T04:00:00.000Z", "updatedAt": "2024-12-17T09:44:45.503Z", "createdAt": "2024-12-14T04:42:52.362Z", "powerConsumptionBreakdown": {"nuclear": 0, "geothermal": 0, "biomass": 0, "coal": 0, "wind": 498, "solar": 0, "hydro": 1240, "gas": 11, "oil": 0, "unknown": 17, "hydro discharge": 0, "battery discharge": 0}, "powerProductionBreakdown": {"nuclear": null, "geothermal": null, "biomass": null, "coal": null, "wind": 134, "solar": 0, "hydro": 1066, "gas": null, "oil": null, "unknown": 21, "hydro discharge": null, "battery discharge": null}, "powerImportBreakdown": {"FI": 0, "NO-NO4": 451, "SE-SE2": 1097}, "powerExportBreakdown": {"FI": 1002, "NO-NO4": 0, "SE-SE2": 0}, "fossilFreePercentage": 99, "renewablePercentage": 99, "powerConsumptionTotal": 1767, "powerProductionTotal": 1221, "powerImportTotal": 1548, "powerExportTotal": 1002, "isEstimated": false, "estimationMethod": null}, {"zone": "SE-SE1", "datetime": "2024-12-17T05:00:00.000Z", "updatedAt": "2024-12-17T08:45:10.021Z", "createdAt": "2024-12-14T05:42:55.579Z", "powerConsumptionBreakdown": {"nuclear": 0, "geothermal": 0, "biomass": 0, "coal": 0, "wind": 238, "solar": 0, "hydro": 1503, "gas": 9, "oil": 0, "unknown": 17, "hydro discharge": 0, "battery discharge": 0}, "powerProductionBreakdown": {"nuclear": null, "geothermal": null, "biomass": null, "coal": null, "wind": 73, "solar": 0, "hydro": 1636, "gas": null, "oil": null, "unknown": 21, "hydro discharge": null, "battery discharge": null}, "powerImportBreakdown": {"FI": 0, "NO-NO4": 394, "SE-SE2": 487}, "powerExportBreakdown": {"FI": 844, "NO-NO4": 0, "SE-SE2": 0}, "fossilFreePercentage": 99, "renewablePercentage": 99, "powerConsumptionTotal": 1767, "powerProductionTotal": 1730, "powerImportTotal": 881, "powerExportTotal": 844, "isEstimated": false, "estimationMethod": null}, {"zone": "SE-SE1", "datetime": "2024-12-17T06:00:00.000Z", "updatedAt": "2024-12-17T10:41:42.876Z", "createdAt": "2024-12-14T06:42:57.461Z", "powerConsumptionBreakdown": {"nuclear": 0, "geothermal": 0, "biomass": 0, "coal": 0, "wind": 155, "solar": 0, "hydro": 1530, "gas": 8, "oil": 0, "unknown": 15, "hydro discharge": 0, "battery discharge": 0}, "powerProductionBreakdown": {"nuclear": null, "geothermal": null, "biomass": null, "coal": null, "wind": 49, "solar": 0, "hydro": 1985, "gas": null, "oil": null, "unknown": 21, "hydro discharge": null, "battery discharge": null}, "powerImportBreakdown": {"FI": 0, "NO-NO4": 381, "SE-SE2": 341}, "powerExportBreakdown": {"FI": 1069, "NO-NO4": 0, "SE-SE2": 0}, "fossilFreePercentage": 99, "renewablePercentage": 99, "powerConsumptionTotal": 1708, "powerProductionTotal": 2055, "powerImportTotal": 722, "powerExportTotal": 1069, "isEstimated": false, "estimationMethod": null}, {"zone": "SE-SE1", "datetime": "2024-12-17T07:00:00.000Z", "updatedAt": "2024-12-17T11:42:49.063Z", "createdAt": "2024-12-14T07:42:48.683Z", "powerConsumptionBreakdown": {"nuclear": 0, "geothermal": 0, "biomass": 0, "coal": 0, "wind": 122, "solar": 0, "hydro": 1616, "gas": 7, "oil": 0, "unknown": 14, "hydro discharge": 0, "battery discharge": 0}, "powerProductionBreakdown": {"nuclear": null, "geothermal": null, "biomass": null, "coal": null, "wind": 36, "solar": 0, "hydro": 2207, "gas": null, "oil": null, "unknown": 19, "hydro discharge": null, "battery discharge": null}, "powerImportBreakdown": {"FI": 0, "NO-NO4": 342, "SE-SE2": 279}, "powerExportBreakdown": {"FI": 1125, "NO-NO4": 0, "SE-SE2": 0}, "fossilFreePercentage": 99, "renewablePercentage": 100, "powerConsumptionTotal": 1758, "powerProductionTotal": 2262, "powerImportTotal": 621, "powerExportTotal": 1125, "isEstimated": false, "estimationMethod": null}, {"zone": "SE-SE1", "datetime": "2024-12-17T08:00:00.000Z", "updatedAt": "2024-12-17T11:42:53.895Z", "createdAt": "2024-12-14T08:41:28.017Z", "powerConsumptionBreakdown": {"nuclear": 0, "geothermal": 0, "biomass": 0, "coal": 0, "wind": 122, "solar": 0, "hydro": 1712, "gas": 7, "oil": 0, "unknown": 14, "hydro discharge": 0, "battery discharge": 0}, "powerProductionBreakdown": {"nuclear": null, "geothermal": null, "biomass": null, "coal": null, "wind": 35, "solar": 0, "hydro": 2305, "gas": null, "oil": null, "unknown": 19, "hydro discharge": null, "battery discharge": null}, "powerImportBreakdown": {"FI": 0, "NO-NO4": 342, "SE-SE2": 279}, "powerExportBreakdown": {"FI": 1125, "NO-NO4": 0, "SE-SE2": 0}, "fossilFreePercentage": 100, "renewablePercentage": 100, "powerConsumptionTotal": 1855, "powerProductionTotal": 2359, "powerImportTotal": 621, "powerExportTotal": 1125, "isEstimated": false, "estimationMethod": null}, {"zone": "SE-SE1", "datetime": "2024-12-17T09:00:00.000Z", "updatedAt": "2024-12-17T11:42:53.895Z", "createdAt": "2024-12-14T09:43:27.969Z", "powerConsumptionBreakdown": {"nuclear": 0, "geothermal": 0, "biomass": 0, "coal": 0, "wind": 167, "solar": 0, "hydro": 2496, "gas": 0, "oil": 0, "unknown": 19, "hydro discharge": 0, "battery discharge": 0}, "powerProductionBreakdown": {"nuclear": null, "geothermal": null, "biomass": null, "coal": null, "wind": 59, "solar": 0, "hydro": 2326, "gas": null, "oil": null, "unknown": 18, "hydro discharge": null, "battery discharge": null}, "powerImportBreakdown": {"SE-SE2": 279}, "powerExportBreakdown": {"SE-SE2": 0}, "fossilFreePercentage": 100, "renewablePercentage": 100, "powerConsumptionTotal": 2682, "powerProductionTotal": 2403, "powerImportTotal": 279, "powerExportTotal": 0, "isEstimated": false, "estimationMethod": null}, {"zone": "SE-SE1", "datetime": "2024-12-17T10:00:00.000Z", "updatedAt": "2024-12-17T11:42:49.063Z", "createdAt": "2024-12-14T10:43:38.313Z", "powerConsumptionBreakdown": {"nuclear": 0, "geothermal": 0, "biomass": 0, "coal": 0, "wind": 59, "solar": 0, "hydro": 2326, "gas": 0, "oil": 0, "unknown": 18, "hydro discharge": 0, "battery discharge": 0}, "powerProductionBreakdown": {"nuclear": null, "geothermal": null, "biomass": null, "coal": null, "wind": 59, "solar": 0, "hydro": 2326, "gas": null, "oil": null, "unknown": 18, "hydro discharge": null, "battery discharge": null}, "powerImportBreakdown": {}, "powerExportBreakdown": {}, "fossilFreePercentage": 100, "renewablePercentage": 100, "powerConsumptionTotal": 2403, "powerProductionTotal": 2403, "powerImportTotal": null, "powerExportTotal": null, "isEstimated": true, "estimationMethod": "TIME_SLICER_AVERAGE"}, {"zone": "SE-SE1", "datetime": "2024-12-17T11:00:00.000Z", "updatedAt": "2024-12-17T11:42:49.063Z", "createdAt": "2024-12-14T11:44:39.536Z", "powerConsumptionBreakdown": {"nuclear": 0, "geothermal": 0, "biomass": 0, "coal": 0, "wind": 63, "solar": 0, "hydro": 2368, "gas": 0, "oil": 0, "unknown": 17, "hydro discharge": 0, "battery discharge": 0}, "powerProductionBreakdown": {"nuclear": null, "geothermal": null, "biomass": null, "coal": null, "wind": 63, "solar": 0, "hydro": 2368, "gas": null, "oil": null, "unknown": 17, "hydro discharge": null, "battery discharge": null}, "powerImportBreakdown": {}, "powerExportBreakdown": {}, "fossilFreePercentage": 100, "renewablePercentage": 100, "powerConsumptionTotal": 2448, "powerProductionTotal": 2448, "powerImportTotal": null, "powerExportTotal": null, "isEstimated": true, "estimationMethod": "TIME_SLICER_AVERAGE"}, {"zone": "SE-SE1", "datetime": "2024-12-17T12:00:00.000Z", "updatedAt": "2024-12-17T11:42:49.063Z", "createdAt": "2024-12-14T12:43:46.959Z", "powerConsumptionBreakdown": {"nuclear": 0, "geothermal": 0, "biomass": 0, "coal": 0, "wind": 70, "solar": 0, "hydro": 2341, "gas": 0, "oil": 0, "unknown": 17, "hydro discharge": 0, "battery discharge": 0}, "powerProductionBreakdown": {"nuclear": null, "geothermal": null, "biomass": null, "coal": null, "wind": 70, "solar": 0, "hydro": 2341, "gas": null, "oil": null, "unknown": 17, "hydro discharge": null, "battery discharge": null}, "powerImportBreakdown": {}, "powerExportBreakdown": {}, "fossilFreePercentage": 100, "renewablePercentage": 100, "powerConsumptionTotal": 2428, "powerProductionTotal": 2428, "powerImportTotal": null, "powerExportTotal": null, "isEstimated": true, "estimationMethod": "TIME_SLICER_AVERAGE"}]}